<ns0:recipe xmlns:ns0="http://fruschtique.de/ns/recipe" xmlns:xsi="http://www.w3.org/2001/XMLSchema-instance" xsi:schemaLocation="http://fruschtique.de/ns/recipe file:///c:/Users/nlutt/Documents/Websites/tools/recipe.xsd" rcpID="ck-842e7574-9f96-4384-9a70-4d6f72ff41f0">
  <ns0:meta>
    <ns0:book />
    <ns0:chapter />
  </ns0:meta>
  <ns0:recipeName>Buddha-Bowl mit H&#252;hnchen, Gr&#252;nkohl, Quinoa und Yumm-Sauce</ns0:recipeName>
  <ns0:recipeKeywords />
  <ns0:recipeIntro />
  <ns0:recipeIngredients>
    <ns0:igdtList>
      <ns0:igdtListName />
      <ns0:igdtListLine>
        <ns0:igdtQuantity>60 g</ns0:igdtQuantity>
        <ns0:igdtName ref="quinoa">Quinoa tricolore</ns0:igdtName>
      </ns0:igdtListLine>
      <ns0:igdtListLine>
        <ns0:igdtQuantity>50 g</ns0:igdtQuantity>
        <ns0:igdtName ref="h&#252;hnerbrust">H&#252;hnerbrust</ns0:igdtName>
      </ns0:igdtListLine>
      <ns0:igdtListLine>
        <ns0:igdtQuantity>40 g</ns0:igdtQuantity>
        <ns0:igdtName ref="avocado">Avocado(s)</ns0:igdtName>
      </ns0:igdtListLine>
      <ns0:igdtListLine>
        <ns0:igdtQuantity>100 g</ns0:igdtQuantity>
        <ns0:igdtName ref="karotte">Karotte(n)</ns0:igdtName>
      </ns0:igdtListLine>
      <ns0:igdtListLine>
        <ns0:igdtQuantity>50 g</ns0:igdtQuantity>
        <ns0:igdtName ref="rotkohl">Rotkohl, frisch</ns0:igdtName>
      </ns0:igdtListLine>
      <ns0:igdtListLine>
        <ns0:igdtQuantity>50 g</ns0:igdtQuantity>
        <ns0:igdtName ref="gr&#252;nkohl">Gr&#252;nkohl, frisch</ns0:igdtName>
      </ns0:igdtListLine>
      <ns0:igdtListLine>
        <ns0:igdtQuantity>50 g</ns0:igdtQuantity>
        <ns0:igdtName ref="gurke">Salatgurke(n)</ns0:igdtName>
      </ns0:igdtListLine>
      <ns0:igdtListLine>
        <ns0:igdtQuantity>50 g</ns0:igdtQuantity>
        <ns0:igdtName ref="orange">Blutorange(n)</ns0:igdtName>
      </ns0:igdtListLine>
      <ns0:igdtListLine>
        <ns0:igdtQuantity>etwas</ns0:igdtQuantity>
        <ns0:igdtName ref="basilikum">Basilikum, frisch</ns0:igdtName>
      </ns0:igdtListLine>
      <ns0:igdtListLine>
        <ns0:igdtQuantity>einige</ns0:igdtQuantity>
        <ns0:igdtName ref="pinienkerne">Pinienkerne</ns0:igdtName>
      </ns0:igdtListLine>
      <ns0:igdtListLine>
        <ns0:igdtQuantity>50 g</ns0:igdtQuantity>
        <ns0:igdtName ref="kichererbsen">Kichererbsen, aus der Dose, abgetropft</ns0:igdtName>
      </ns0:igdtListLine>
      <ns0:igdtListLine>
        <ns0:igdtQuantity>1 Zehe/n</ns0:igdtQuantity>
        <ns0:igdtName ref="knoblauch">Knoblauch</ns0:igdtName>
      </ns0:igdtListLine>
      <ns0:igdtListLine>
        <ns0:igdtQuantity>50 g</ns0:igdtQuantity>
        <ns0:igdtName ref="tofu">Seidentofu</ns0:igdtName>
      </ns0:igdtListLine>
      <ns0:igdtListLine>
        <ns0:igdtQuantity>50 ml</ns0:igdtQuantity>
        <ns0:igdtName ref="kokosmilch">Kokosmilch, fettreduziert</ns0:igdtName>
      </ns0:igdtListLine>
      <ns0:igdtListLine>
        <ns0:igdtQuantity>15 ml</ns0:igdtQuantity>
        <ns0:igdtName ref="zitrone">Zitronensaft</ns0:igdtName>
      </ns0:igdtListLine>
      <ns0:igdtListLine>
        <ns0:igdtQuantity>&#188; TL</ns0:igdtQuantity>
        <ns0:igdtName ref="curry">Curry</ns0:igdtName>
      </ns0:igdtListLine>
      <ns0:igdtListLine>
        <ns0:igdtQuantity>25 g</ns0:igdtQuantity>
        <ns0:igdtName ref="hefe">Hefeflocken</ns0:igdtName>
      </ns0:igdtListLine>
      <ns0:igdtListLine>
        <ns0:igdtQuantity>&#188; TL</ns0:igdtQuantity>
        <ns0:igdtName ref="">Meersalz</ns0:igdtName>
      </ns0:igdtListLine>
      <ns0:igdtListLine>
        <ns0:igdtQuantity>30 ml</ns0:igdtQuantity>
        <ns0:igdtName ref="kichererbsen">Sud, aufgefangen, aus der Dose mit den Kichererbsen</ns0:igdtName>
      </ns0:igdtListLine>
    </ns0:igdtList>
  </ns0:recipeIngredients>
  <ns0:recipeInstructions>
    <ns0:instruction>
      <ns0:instrStepName />
      <ns0:instrStepText>Den Quinoa in einem Sieb abwaschen und mit der doppelten Menge Wasser und etwas Salz in einem Topf mit Deckel zum Kochen bringen. Anschlie&#223;end bei geringer Hitze ca. 20 Minuten k&#246;cheln lassen.
In der Zwischenzeit das H&#252;hnchen salzen, in einer antihaftbeschichteten Pfanne von beiden Seiten ca. 5 Minuten anbraten und in Scheiben schneiden. M&#246;hren sch&#228;len und in d&#252;nne Stifte schneiden. Rotkohl waschen und in feine Streifen schneiden. Gr&#252;nkohl waschen, die harten Rippen entfernen und die Bl&#228;tter in feine Streifen schneiden. Die Gurke waschen und in d&#252;nne Scheiben schneiden. Die Blutorange sch&#228;len und ebenfalls in Scheiben schneiden. Die Basilikumbl&#228;tter beiseitestellen.
F&#252;r das Dressing alle Zutaten, bis auf den Kichererbsensaft, in den Mixer geben. Alles glatt p&#252;rieren und nach und nach den Kichererbsensaft hinzuf&#252;gen. W&#228;hrenddessen so lange weiter r&#252;hren, bis die Sauce eine dickliche Konsistenz bekommt.
Die Zutaten f&#252;r die Bowl in einer Sch&#252;ssel anrichten und das Dressing dar&#252;ber verteilen.</ns0:instrStepText>
    </ns0:instruction>
  </ns0:recipeInstructions>
  <ns0:recipeSideDish />
  <ns0:recipeOrigin />
  <ns0:recipeSeeAlso />
  <ns0:recipeLicense />
</ns0:recipe>