<ns0:recipe xmlns:ns0="http://fruschtique.de/ns/recipe" xmlns:xsi="http://www.w3.org/2001/XMLSchema-instance" xsi:schemaLocation="http://fruschtique.de/ns/recipe file:///c:/Users/nlutt/Documents/Websites/tools/recipe.xsd" rcpID="ck-f4a39e0d-0d06-4101-8143-223a0db4c876">
  <ns0:meta>
    <ns0:book />
    <ns0:chapter />
  </ns0:meta>
  <ns0:recipeName>Gr&#252;nkohl mit Bregenwurst</ns0:recipeName>
  <ns0:recipeKeywords />
  <ns0:recipeIntro />
  <ns0:recipeIngredients>
    <ns0:igdtList>
      <ns0:igdtListName />
      <ns0:igdtListLine>
        <ns0:igdtQuantity>1 &#189; kg</ns0:igdtQuantity>
        <ns0:igdtName ref="gr&#252;nkohl">Gr&#252;nkohl</ns0:igdtName>
      </ns0:igdtListLine>
      <ns0:igdtListLine>
        <ns0:igdtQuantity>75 g</ns0:igdtQuantity>
        <ns0:igdtName ref="r&#228;ucherspeck">R&#228;ucherspeck</ns0:igdtName>
      </ns0:igdtListLine>
      <ns0:igdtListLine>
        <ns0:igdtQuantity>1 EL</ns0:igdtQuantity>
        <ns0:igdtName ref="schweineschmalz">Schweineschmalz</ns0:igdtName>
      </ns0:igdtListLine>
      <ns0:igdtListLine>
        <ns0:igdtQuantity>500 g</ns0:igdtQuantity>
        <ns0:igdtName ref="kasseler">Kasseler</ns0:igdtName>
      </ns0:igdtListLine>
      <ns0:igdtListLine>
        <ns0:igdtQuantity>500 g</ns0:igdtQuantity>
        <ns0:igdtName ref="wurst">Kohlwurst (Bregenwurst)</ns0:igdtName>
      </ns0:igdtListLine>
    </ns0:igdtList>
  </ns0:recipeIngredients>
  <ns0:recipeInstructions>
    <ns0:instruction>
      <ns0:instrStepName />
      <ns0:instrStepText>Den Gr&#252;nkohl putzen, waschen und abtropfen lassen. Sehr fein hacken.
Den Speck w&#252;rfeln, im Schweineschmalz auslassen. Das Kassler grob w&#252;rfeln, zugeben und anbraten. Den Gr&#252;nkohl untermengen und 30 Minuten zugedeckt bei schwacher Hitze garen. Die Bregenwurst oben darauf legen. Im Rohr bei Mittelhitze weitere 30 Minuten garen.
Mit Kartoffeln servieren.</ns0:instrStepText>
    </ns0:instruction>
  </ns0:recipeInstructions>
  <ns0:recipeSideDish />
  <ns0:recipeOrigin />
  <ns0:recipeSeeAlso />
  <ns0:recipeLicense />
</ns0:recipe>