<ns0:recipe xmlns:ns0="http://fruschtique.de/ns/recipe" xmlns:xsi="http://www.w3.org/2001/XMLSchema-instance" xsi:schemaLocation="http://fruschtique.de/ns/recipe file:///c:/Users/nlutt/Documents/Websites/tools/recipe.xsd" rcpID="ck-3850c0d1-8262-4529-9bf0-a0bcfc6c58cb">
  <ns0:meta>
    <ns0:book />
    <ns0:chapter />
  </ns0:meta>
  <ns0:recipeName>Gr&#252;nkohl-Mais-Brot mit K&#252;mmel und M&#252;sli</ns0:recipeName>
  <ns0:recipeKeywords />
  <ns0:recipeIntro />
  <ns0:recipeIngredients>
    <ns0:igdtList>
      <ns0:igdtListName />
      <ns0:igdtListLine>
        <ns0:igdtQuantity>&#189; W&#252;rfel</ns0:igdtQuantity>
        <ns0:igdtName ref="hefe">Frischhefe</ns0:igdtName>
      </ns0:igdtListLine>
      <ns0:igdtListLine>
        <ns0:igdtQuantity>1 TL</ns0:igdtQuantity>
        <ns0:igdtName ref="zucker">Zucker</ns0:igdtName>
      </ns0:igdtListLine>
      <ns0:igdtListLine>
        <ns0:igdtQuantity>250 g</ns0:igdtQuantity>
        <ns0:igdtName ref="weizenmehl">Weizenvollkornmehl</ns0:igdtName>
      </ns0:igdtListLine>
      <ns0:igdtListLine>
        <ns0:igdtQuantity>250 g</ns0:igdtQuantity>
        <ns0:igdtName ref="weizenmehl">Weizenmehl</ns0:igdtName>
      </ns0:igdtListLine>
      <ns0:igdtListLine>
        <ns0:igdtQuantity>3 EL</ns0:igdtQuantity>
        <ns0:igdtName ref="oliven&#246;l">Oliven&#246;l</ns0:igdtName>
      </ns0:igdtListLine>
      <ns0:igdtListLine>
        <ns0:igdtQuantity>1 TL</ns0:igdtQuantity>
        <ns0:igdtName ref="">Salz</ns0:igdtName>
      </ns0:igdtListLine>
      <ns0:igdtListLine>
        <ns0:igdtQuantity>300 g</ns0:igdtQuantity>
        <ns0:igdtName ref="gr&#252;nkohl">Gr&#252;nkohl</ns0:igdtName>
      </ns0:igdtListLine>
      <ns0:igdtListLine>
        <ns0:igdtQuantity>3 EL</ns0:igdtQuantity>
        <ns0:igdtName ref="mais">Mais</ns0:igdtName>
      </ns0:igdtListLine>
      <ns0:igdtListLine>
        <ns0:igdtQuantity>&#189; TL</ns0:igdtQuantity>
        <ns0:igdtName ref="k&#252;mmel">K&#252;mmelpulver</ns0:igdtName>
      </ns0:igdtListLine>
      <ns0:igdtListLine>
        <ns0:igdtQuantity>&#189; TL</ns0:igdtQuantity>
        <ns0:igdtName ref="k&#252;mmel">K&#252;mmel, ganz</ns0:igdtName>
      </ns0:igdtListLine>
      <ns0:igdtListLine>
        <ns0:igdtQuantity>3 EL</ns0:igdtQuantity>
        <ns0:igdtName ref="sultaninen">M&#252;sli (Basism&#252;sli ohne Rosinen)</ns0:igdtName>
      </ns0:igdtListLine>
    </ns0:igdtList>
  </ns0:recipeIngredients>
  <ns0:recipeInstructions>
    <ns0:instruction>
      <ns0:instrStepName />
      <ns0:instrStepText>Die Hefe zerbr&#246;seln, mit etwas lauwarmem Wasser und einem Teil des Weizenmehls sowie dem Zucker verr&#252;hren und eine Viertelstunde gehen lassen.
Den Gr&#252;nkohl von den Stielen zupfen, waschen und hacken.
Restliches Mehl, M&#252;sli, &#214;l, K&#252;mmel und Salz zum Vorteig hinzuf&#252;gen, lauwarmes Wasser nach Bedarf dazugeben. Den Teig noch einmal ca. eine halbe Stunde zugedeckt an einem warmen Ort gehen lassen, oder wenn es schnell gehen soll, direkt fortfahren.
Den Gr&#252;nkohl und den Mais hinzuf&#252;gen, alles noch einmal gut durchkneten. Den Teigling von allen Seiten leicht bemehlen und in einer Sch&#252;ssel nochmals gehen lassen, optimalerweise ca eine Stunde.
Den Brotlaib auf ein Backblech legen und mit Wasser einpinseln. Wer mag, streut noch ein paar M&#252;sliflocken oder K&#246;rner darauf.
Dann das Brot im hei&#223;en Backofen bei 220 &#176;C Umluft ca. 40 Minuten backen. Das Brot ist fertig, wenn es beim Draufklopfen hohl klingt oder ein hineingepikstes Messer ohne Teigreste wieder herauskommt. Tipp: Sch&#246;n knusprig w&#252;rde es, wenn das noch hei&#223;e Brot abermals mit Wasser eingepinselt wird und dann ausk&#252;hlen darf.
Dazu passt z. B. veganer Frischk&#228;se oder ein anderer schlichter Aufstrich.</ns0:instrStepText>
    </ns0:instruction>
  </ns0:recipeInstructions>
  <ns0:recipeSideDish />
  <ns0:recipeOrigin />
  <ns0:recipeSeeAlso />
  <ns0:recipeLicense />
</ns0:recipe>