<ns0:recipe xmlns:ns0="http://fruschtique.de/ns/recipe" xmlns:xsi="http://www.w3.org/2001/XMLSchema-instance" xsi:schemaLocation="http://fruschtique.de/ns/recipe file:///c:/Users/nlutt/Documents/Websites/tools/recipe.xsd" rcpID="ck-125d4114-8afd-48a9-8354-f20b4b7c540d">
  <ns0:meta>
    <ns0:book />
    <ns0:chapter />
  </ns0:meta>
  <ns0:recipeName>Gr&#252;nkohl mit Mettw&#252;rsten</ns0:recipeName>
  <ns0:recipeKeywords />
  <ns0:recipeIntro />
  <ns0:recipeIngredients>
    <ns0:igdtList>
      <ns0:igdtListName />
      <ns0:igdtListLine>
        <ns0:igdtQuantity>3 Gl&#228;ser</ns0:igdtQuantity>
        <ns0:igdtName ref="gr&#252;nkohl">Gr&#252;nkohl, a 800 g</ns0:igdtName>
      </ns0:igdtListLine>
      <ns0:igdtListLine>
        <ns0:igdtQuantity>1 EL</ns0:igdtQuantity>
        <ns0:igdtName ref="g&#228;nseschmalz">Schmalz, (G&#228;nseschmalz)</ns0:igdtName>
      </ns0:igdtListLine>
      <ns0:igdtListLine>
        <ns0:igdtQuantity>1 gro&#223;e</ns0:igdtQuantity>
        <ns0:igdtName ref="zwiebel">Zwiebel(n), gehackt</ns0:igdtName>
      </ns0:igdtListLine>
      <ns0:igdtListLine>
        <ns0:igdtQuantity>6</ns0:igdtQuantity>
        <ns0:igdtName ref="wurst">W&#252;rste, Mettw&#252;rste geschnitten</ns0:igdtName>
      </ns0:igdtListLine>
      <ns0:igdtListLine>
        <ns0:igdtQuantity />
        <ns0:igdtName ref="pfeffer">Pfeffer, (nach Belieben)</ns0:igdtName>
      </ns0:igdtListLine>
      <ns0:igdtListLine>
        <ns0:igdtQuantity>1 EL</ns0:igdtQuantity>
        <ns0:igdtName ref="br&#252;he">Br&#252;he, (Suppenbr&#252;he), instant</ns0:igdtName>
      </ns0:igdtListLine>
    </ns0:igdtList>
  </ns0:recipeIngredients>
  <ns0:recipeInstructions>
    <ns0:instruction>
      <ns0:instrStepName />
      <ns0:instrStepText>G&#228;nseschmalz in einem Topf schmelzen lassen und die gehackten Zwiebeln and&#252;nsten und den Gr&#252;nkohl zugeben mit den klein geschnittenen Mettw&#252;rsten, ca. 30 Minuten k&#246;cheln lassen.
W&#252;rzen mit nicht aufgel&#246;stem Suppenbr&#252;hepulver und Pfeffer.
Dazu schmecken Salzkartoffeln oder Bratkartoffeln.</ns0:instrStepText>
    </ns0:instruction>
  </ns0:recipeInstructions>
  <ns0:recipeSideDish />
  <ns0:recipeOrigin />
  <ns0:recipeSeeAlso />
  <ns0:recipeLicense />
</ns0:recipe>